{
  "generated_at": "2026-06-26 22:39:38.951654",
  "total": 4,
  "strategies": [
    {
      "id": "convergence",
      "name": "均线收敛发散",
      "description": "月末选均线最收敛top20%等权·开源证券(91)",
      "source": "开源证券",
      "total_return": 2494.8,
      "annual_return": 25.2,
      "max_drawdown": 39.0,
      "sharpe": 1.51,
      "calmar": 0.65,
      "annual_vol": 55.9,
      "total_value_10k": 274366.0,
      "rebalance": "monthly",
      "start_date": "2010-01-31",
      "end_date": "2024-10-31",
      "nav_history": [
        {
          "date": "2010-01-31",
          "nav": 1.0
        },
        {
          "date": "2011-10-31",
          "nav": 1.2733
        },
        {
          "date": "2013-01-31",
          "nav": 1.9869
        },
        {
          "date": "2014-04-30",
          "nav": 2.6585
        },
        {
          "date": "2015-07-31",
          "nav": 7.2097
        },
        {
          "date": "2016-10-31",
          "nav": 10.0039
        },
        {
          "date": "2018-01-31",
          "nav": 8.5005
        },
        {
          "date": "2019-04-30",
          "nav": 8.755
        },
        {
          "date": "2020-07-31",
          "nav": 10.272
        },
        {
          "date": "2021-10-31",
          "nav": 13.1661
        },
        {
          "date": "2023-01-31",
          "nav": 20.8911
        },
        {
          "date": "2024-04-30",
          "nav": 22.1003
        }
      ]
    },
    {
      "id": "etf_top10",
      "name": "ETF TOP10轮动",
      "description": "每年末选收益率最高10只ETF等权，半年调仓",
      "source": "自研",
      "total_return": 104.5,
      "annual_return": 19.8,
      "max_drawdown": 24.5,
      "sharpe": 0.92,
      "calmar": 0,
      "annual_vol": 0,
      "total_value_10k": 0,
      "rebalance": "semi-annual",
      "start_date": "2022-05-12",
      "end_date": "2026-06-26",
      "nav_history": [
        {
          "date": "2022-05-12",
          "nav": 1.0
        },
        {
          "date": "2022-05-31",
          "nav": 1.0067
        },
        {
          "date": "2022-06-22",
          "nav": 1.0322
        },
        {
          "date": "2022-07-13",
          "nav": 1.0389
        },
        {
          "date": "2022-08-03",
          "nav": 1.028
        },
        {
          "date": "2022-08-24",
          "nav": 1.0327
        },
        {
          "date": "2022-09-15",
          "nav": 1.0105
        },
        {
          "date": "2022-10-13",
          "nav": 0.9989
        },
        {
          "date": "2022-11-03",
          "nav": 1.006
        },
        {
          "date": "2022-11-24",
          "nav": 1.0052
        },
        {
          "date": "2022-12-15",
          "nav": 1.0107
        },
        {
          "date": "2023-01-06",
          "nav": 1.0142
        },
        {
          "date": "2023-02-03",
          "nav": 1.0298
        },
        {
          "date": "2023-02-24",
          "nav": 1.0144
        },
        {
          "date": "2023-03-17",
          "nav": 1.0014
        },
        {
          "date": "2023-04-10",
          "nav": 1.016
        },
        {
          "date": "2023-05-04",
          "nav": 1.0002
        },
        {
          "date": "2023-05-25",
          "nav": 0.994
        },
        {
          "date": "2023-06-15",
          "nav": 0.9935
        },
        {
          "date": "2023-07-10",
          "nav": 0.9894
        },
        {
          "date": "2023-07-31",
          "nav": 0.9964
        },
        {
          "date": "2023-08-21",
          "nav": 0.9762
        },
        {
          "date": "2023-09-11",
          "nav": 0.9721
        },
        {
          "date": "2023-10-10",
          "nav": 0.9601
        },
        {
          "date": "2023-10-31",
          "nav": 0.9577
        },
        {
          "date": "2023-11-21",
          "nav": 0.9751
        },
        {
          "date": "2023-12-12",
          "nav": 0.9475
        },
        {
          "date": "2024-01-03",
          "nav": 0.9146
        },
        {
          "date": "2024-01-24",
          "nav": 0.8528
        },
        {
          "date": "2024-02-22",
          "nav": 0.8907
        },
        {
          "date": "2024-03-14",
          "nav": 0.9406
        },
        {
          "date": "2024-04-08",
          "nav": 0.9057
        },
        {
          "date": "2024-04-29",
          "nav": 0.9427
        },
        {
          "date": "2024-05-23",
          "nav": 0.9252
        },
        {
          "date": "2024-06-14",
          "nav": 0.9142
        },
        {
          "date": "2024-07-05",
          "nav": 0.8652
        },
        {
          "date": "2024-07-26",
          "nav": 0.8658
        },
        {
          "date": "2024-08-16",
          "nav": 0.8444
        },
        {
          "date": "2024-09-06",
          "nav": 0.8112
        },
        {
          "date": "2024-10-08",
          "nav": 1.2503
        },
        {
          "date": "2024-10-29",
          "nav": 1.0941
        },
        {
          "date": "2024-11-19",
          "nav": 1.1119
        },
        {
          "date": "2024-12-10",
          "nav": 1.1193
        },
        {
          "date": "2024-12-31",
          "nav": 1.0903
        },
        {
          "date": "2025-01-22",
          "nav": 1.1051
        },
        {
          "date": "2025-02-20",
          "nav": 1.1494
        },
        {
          "date": "2025-03-13",
          "nav": 1.1098
        },
        {
          "date": "2025-04-03",
          "nav": 1.1079
        },
        {
          "date": "2025-04-25",
          "nav": 1.1116
        },
        {
          "date": "2025-05-21",
          "nav": 1.1536
        },
        {
          "date": "2025-06-12",
          "nav": 1.1714
        },
        {
          "date": "2025-07-03",
          "nav": 1.2073
        },
        {
          "date": "2025-07-24",
          "nav": 1.248
        },
        {
          "date": "2025-08-14",
          "nav": 1.2939
        },
        {
          "date": "2025-09-04",
          "nav": 1.3493
        },
        {
          "date": "2025-09-25",
          "nav": 1.4387
        },
        {
          "date": "2025-10-24",
          "nav": 1.4917
        },
        {
          "date": "2025-11-14",
          "nav": 1.4735
        },
        {
          "date": "2025-12-05",
          "nav": 1.4816
        },
        {
          "date": "2025-12-26",
          "nav": 1.5266
        },
        {
          "date": "2026-01-20",
          "nav": 1.589
        },
        {
          "date": "2026-02-10",
          "nav": 1.5903
        },
        {
          "date": "2026-03-11",
          "nav": 1.5903
        },
        {
          "date": "2026-04-01",
          "nav": 1.5264
        },
        {
          "date": "2026-04-23",
          "nav": 1.7897
        },
        {
          "date": "2026-05-19",
          "nav": 1.9381
        },
        {
          "date": "2026-06-09",
          "nav": 1.9348
        }
      ]
    },
    {
      "id": "network",
      "name": "网络中心度CC",
      "description": "月末选网络中心度最高top20%等权·华西证券",
      "source": "华西证券",
      "total_return": 515.8,
      "annual_return": 13.0,
      "max_drawdown": 37.5,
      "sharpe": 0.99,
      "calmar": 0.35,
      "annual_vol": 50.8,
      "total_value_10k": 64172.0,
      "rebalance": "monthly",
      "start_date": "2010-02-28",
      "end_date": "2024-11-30",
      "nav_history": [
        {
          "date": "2010-02-28",
          "nav": 1.0
        },
        {
          "date": "2011-05-31",
          "nav": 1.0785
        },
        {
          "date": "2012-08-31",
          "nav": 0.9533
        },
        {
          "date": "2013-11-30",
          "nav": 1.1456
        },
        {
          "date": "2015-02-28",
          "nav": 2.74
        },
        {
          "date": "2016-05-31",
          "nav": 3.0392
        },
        {
          "date": "2017-08-31",
          "nav": 3.6042
        },
        {
          "date": "2018-11-30",
          "nav": 2.4193
        },
        {
          "date": "2020-02-29",
          "nav": 2.8492
        },
        {
          "date": "2021-05-31",
          "nav": 3.457
        },
        {
          "date": "2022-08-31",
          "nav": 4.107
        },
        {
          "date": "2023-11-30",
          "nav": 4.9568
        }
      ]
    },
    {
      "id": "vol_mom",
      "name": "价量共振VM",
      "description": "价格动量×成交量动量信号择时，月度调仓",
      "source": "Hugo原创",
      "total_return": 303.6,
      "annual_return": 10.1,
      "max_drawdown": 47.1,
      "sharpe": 0.88,
      "calmar": 0.21,
      "annual_vol": 47.8,
      "total_value_10k": 44357.0,
      "rebalance": "monthly",
      "start_date": "2010-01-31",
      "end_date": "2024-10-31",
      "nav_history": [
        {
          "date": "2010-01-31",
          "nav": 1.0
        },
        {
          "date": "2010-09-30",
          "nav": 1.2106
        },
        {
          "date": "2010-12-31",
          "nav": 1.0417
        },
        {
          "date": "2011-03-31",
          "nav": 1.2004
        },
        {
          "date": "2011-06-30",
          "nav": 1.1368
        },
        {
          "date": "2011-09-30",
          "nav": 1.0364
        },
        {
          "date": "2011-12-31",
          "nav": 0.8896
        },
        {
          "date": "2012-03-31",
          "nav": 1.0721
        },
        {
          "date": "2012-06-30",
          "nav": 1.0058
        },
        {
          "date": "2012-09-30",
          "nav": 1.0882
        },
        {
          "date": "2012-12-31",
          "nav": 1.2167
        },
        {
          "date": "2013-03-31",
          "nav": 1.1886
        },
        {
          "date": "2013-06-30",
          "nav": 1.1658
        },
        {
          "date": "2013-09-30",
          "nav": 1.3265
        },
        {
          "date": "2013-12-31",
          "nav": 1.2784
        },
        {
          "date": "2014-03-31",
          "nav": 1.3158
        },
        {
          "date": "2014-06-30",
          "nav": 1.4212
        },
        {
          "date": "2014-09-30",
          "nav": 1.6699
        },
        {
          "date": "2014-12-31",
          "nav": 2.0239
        },
        {
          "date": "2015-03-31",
          "nav": 3.1602
        },
        {
          "date": "2015-06-30",
          "nav": 2.6997
        },
        {
          "date": "2015-09-30",
          "nav": 2.9142
        },
        {
          "date": "2015-12-31",
          "nav": 2.3379
        },
        {
          "date": "2016-03-31",
          "nav": 2.7755
        },
        {
          "date": "2016-06-30",
          "nav": 2.7357
        },
        {
          "date": "2016-09-30",
          "nav": 3.0289
        },
        {
          "date": "2016-12-31",
          "nav": 3.0715
        },
        {
          "date": "2017-03-31",
          "nav": 2.9941
        },
        {
          "date": "2017-06-30",
          "nav": 2.9135
        },
        {
          "date": "2017-09-30",
          "nav": 2.8281
        },
        {
          "date": "2017-12-31",
          "nav": 2.6896
        },
        {
          "date": "2018-03-31",
          "nav": 2.4603
        },
        {
          "date": "2018-06-30",
          "nav": 2.2628
        },
        {
          "date": "2018-09-30",
          "nav": 1.9238
        },
        {
          "date": "2018-12-31",
          "nav": 2.0576
        },
        {
          "date": "2019-03-31",
          "nav": 2.7493
        },
        {
          "date": "2019-07-31",
          "nav": 2.4669
        },
        {
          "date": "2019-10-31",
          "nav": 2.4255
        },
        {
          "date": "2020-01-31",
          "nav": 2.2759
        },
        {
          "date": "2020-04-30",
          "nav": 2.3108
        },
        {
          "date": "2020-07-31",
          "nav": 2.6975
        },
        {
          "date": "2020-10-31",
          "nav": 2.7373
        },
        {
          "date": "2021-01-31",
          "nav": 2.7075
        },
        {
          "date": "2021-04-30",
          "nav": 2.9777
        },
        {
          "date": "2021-07-31",
          "nav": 3.0698
        },
        {
          "date": "2021-10-31",
          "nav": 3.0947
        },
        {
          "date": "2022-01-31",
          "nav": 3.2831
        },
        {
          "date": "2022-04-30",
          "nav": 3.1173
        },
        {
          "date": "2022-07-31",
          "nav": 3.4167
        },
        {
          "date": "2022-10-31",
          "nav": 3.7227
        },
        {
          "date": "2023-01-31",
          "nav": 3.9085
        },
        {
          "date": "2023-04-30",
          "nav": 3.6248
        },
        {
          "date": "2023-07-31",
          "nav": 3.616
        },
        {
          "date": "2023-10-31",
          "nav": 3.6828
        },
        {
          "date": "2024-01-31",
          "nav": 3.616
        },
        {
          "date": "2024-04-30",
          "nav": 3.5602
        },
        {
          "date": "2024-07-31",
          "nav": 3.126
        },
        {
          "date": "2024-10-31",
          "nav": 4.4357
        }
      ]
    }
  ]
}